<?xml version = "1.0" encoding="UTF-8" standalone="yes"?>
<CPLEXSolution version="1.2">
 <header
   problemName="../models/dfmodel1/npu/ilp/subgraphs-subgraph-1.lp"
   solutionName="incumbent"
   solutionIndex="-1"
   objectiveValue="0.48319699999990373"
   solutionTypeValue="3"
   solutionTypeString="primal"
   solutionStatusValue="101"
   solutionStatusString="integer optimal solution"
   solutionMethodString="mip"
   primalFeasible="1"
   dualFeasible="1"
   MIPNodes="0"
   MIPIterations="169"
   writeLevel="1"/>
 <quality
   epInt="1.0000000000000001e-05"
   epRHS="9.9999999999999995e-07"
   maxIntInfeas="0"
   maxPrimalInfeas="2.8438362775773385e-13"
   maxX="999.82264300000008"
   maxSlack="3999.5400340000006"/>
 <linearConstraints>
  <constraint name="c1" index="0" slack="-0.48319699999990373"/>
  <constraint name="c2" index="1" slack="-1000.0852489999999"/>
  <constraint name="c3" index="2" slack="-1000.4831969999999"/>
  <constraint name="c4" index="3" slack="-0.11286999999992986"/>
  <constraint name="c5" index="4" slack="-0.48319699999990373"/>
  <constraint name="c6" index="5" slack="-999.56833900000004"/>
  <constraint name="c7" index="6" slack="-1000.4831969999999"/>
  <constraint name="c8" index="7" slack="0"/>
  <constraint name="c9" index="8" slack="-0.48319699999990373"/>
  <constraint name="c10" index="9" slack="-0.38153299999987667"/>
  <constraint name="c11" index="10" slack="-1000.4831969999999"/>
  <constraint name="c12" index="11" slack="-0.38153299999987667"/>
  <constraint name="c13" index="12" slack="-0.48319699999990373"/>
  <constraint name="c14" index="13" slack="-900.07862799999998"/>
  <constraint name="c15" index="14" slack="-1000.4831969999999"/>
  <constraint name="c16" index="15" slack="-0.03345600000000104"/>
  <constraint name="c17" index="16" slack="-0.48319699999990373"/>
  <constraint name="c18" index="17" slack="-900.45369299999993"/>
  <constraint name="c19" index="18" slack="-1000.4831969999999"/>
  <constraint name="c20" index="19" slack="-0.42494099999987611"/>
  <constraint name="c21" index="20" slack="-0.48319699999990373"/>
  <constraint name="c22" index="21" slack="-900.13943699999993"/>
  <constraint name="c23" index="22" slack="-1000.4831969999999"/>
  <constraint name="c24" index="23" slack="-0.078627999999980602"/>
  <constraint name="c25" index="24" slack="-0.48319699999990373"/>
  <constraint name="c26" index="25" slack="-900.4831969999999"/>
  <constraint name="c27" index="26" slack="-1000.4831969999999"/>
  <constraint name="c28" index="27" slack="-0.45369299999993018"/>
  <constraint name="c29" index="28" slack="-1000.4831969999999"/>
  <constraint name="c30" index="29" slack="-0.13943699999992987"/>
  <constraint name="c31" index="30" slack="-0.48319699999990373"/>
  <constraint name="c32" index="31" slack="-900.39985499999989"/>
  <constraint name="c33" index="32" slack="-0.48319699999990373"/>
  <constraint name="c34" index="33" slack="-1000.2005880000002"/>
  <constraint name="c35" index="34" slack="-1000.4831969999999"/>
  <constraint name="c36" index="35" slack="-0.39985499999988861"/>
  <constraint name="c37" index="36" slack="0"/>
  <constraint name="c38" index="37" slack="0"/>
  <constraint name="c39" index="38" slack="0"/>
  <constraint name="c40" index="39" slack="0"/>
  <constraint name="c41" index="40" slack="0"/>
  <constraint name="c42" index="41" slack="0"/>
  <constraint name="c43" index="42" slack="0"/>
  <constraint name="c44" index="43" slack="0"/>
  <constraint name="c45" index="44" slack="0"/>
  <constraint name="c46" index="45" slack="-998"/>
  <constraint name="c47" index="46" slack="-1"/>
  <constraint name="c48" index="47" slack="-2999.1868060000002"/>
  <constraint name="c49" index="48" slack="0"/>
  <constraint name="c50" index="49" slack="-999"/>
  <constraint name="c51" index="50" slack="-999.61846700000012"/>
  <constraint name="c52" index="51" slack="0"/>
  <constraint name="c53" index="52" slack="0"/>
  <constraint name="c54" index="53" slack="0"/>
  <constraint name="c55" index="54" slack="0"/>
  <constraint name="c56" index="55" slack="-998"/>
  <constraint name="c57" index="56" slack="-1"/>
  <constraint name="c58" index="57" slack="-2899.6970950000004"/>
  <constraint name="c59" index="58" slack="0"/>
  <constraint name="c60" index="59" slack="-999"/>
  <constraint name="c61" index="60" slack="-999.65192300000012"/>
  <constraint name="c62" index="61" slack="-998"/>
  <constraint name="c63" index="62" slack="-1"/>
  <constraint name="c64" index="63" slack="-2899.7579040000001"/>
  <constraint name="c65" index="64" slack="0"/>
  <constraint name="c66" index="65" slack="-999"/>
  <constraint name="c67" index="66" slack="-999.6970950000001"/>
  <constraint name="c68" index="67" slack="-999"/>
  <constraint name="c69" index="68" slack="0"/>
  <constraint name="c70" index="69" slack="-1999.7579040000001"/>
  <constraint name="c71" index="70" slack="-999"/>
  <constraint name="c72" index="71" slack="0"/>
  <constraint name="c73" index="72" slack="-2900.0183219999999"/>
  <constraint name="c74" index="73" slack="-998"/>
  <constraint name="c75" index="74" slack="-1"/>
  <constraint name="c76" index="75" slack="-2999.8190550000004"/>
  <constraint name="c77" index="76" slack="0"/>
  <constraint name="c78" index="77" slack="-999"/>
  <constraint name="c79" index="78" slack="-0.01832200000001194"/>
  <constraint name="c80" index="79" slack="-998"/>
  <constraint name="c81" index="80" slack="-1"/>
  <constraint name="c82" index="81" slack="-2000.0517929999999"/>
  <constraint name="c83" index="82" slack="0"/>
  <constraint name="c84" index="83" slack="-999"/>
  <constraint name="c85" index="84" slack="-0.079413999999928819"/>
  <constraint name="c86" index="85" slack="-998"/>
  <constraint name="c87" index="86" slack="-1"/>
  <constraint name="c88" index="87" slack="-2000.3480769999999"/>
  <constraint name="c89" index="88" slack="0"/>
  <constraint name="c90" index="89" slack="-999"/>
  <constraint name="c91" index="90" slack="-0.34807699999987562"/>
  <constraint name="c92" index="91" slack="-900.04517199999998"/>
  <constraint name="c93" index="92" slack="0"/>
  <constraint name="c94" index="93" slack="-900.04517199999998"/>
  <constraint name="c95" index="94" slack="0"/>
  <constraint name="c96" index="95" slack="-998"/>
  <constraint name="c97" index="96" slack="-1"/>
  <constraint name="c98" index="97" slack="-2900.4202369999998"/>
  <constraint name="c99" index="98" slack="0"/>
  <constraint name="c100" index="99" slack="-999"/>
  <constraint name="c101" index="100" slack="-0.39148499999987507"/>
  <constraint name="c102" index="101" slack="-998"/>
  <constraint name="c103" index="102" slack="-1"/>
  <constraint name="c104" index="103" slack="-2900.4497409999999"/>
  <constraint name="c105" index="104" slack="0"/>
  <constraint name="c106" index="105" slack="-999"/>
  <constraint name="c107" index="106" slack="-0.42023699999992914"/>
  <constraint name="c108" index="107" slack="-998"/>
  <constraint name="c109" index="108" slack="-1"/>
  <constraint name="c110" index="109" slack="-2998.9077849999999"/>
  <constraint name="c111" index="110" slack="0"/>
  <constraint name="c112" index="111" slack="-999"/>
  <constraint name="c113" index="112" slack="-999.60014500000011"/>
  <constraint name="c114" index="113" slack="-998"/>
  <constraint name="c115" index="114" slack="-1"/>
  <constraint name="c116" index="115" slack="-3899.4180740000002"/>
  <constraint name="c117" index="116" slack="0"/>
  <constraint name="c118" index="117" slack="-999"/>
  <constraint name="c119" index="118" slack="-999.63360100000011"/>
  <constraint name="c120" index="119" slack="-1899.7931390000001"/>
  <constraint name="c121" index="120" slack="-999.76438700000006"/>
  <constraint name="c122" index="121" slack="-900.05383800000004"/>
  <constraint name="c123" index="122" slack="-0.025085999999987507"/>
  <constraint name="c124" index="123" slack="-998"/>
  <constraint name="c125" index="124" slack="-1"/>
  <constraint name="c126" index="125" slack="-3899.4788830000002"/>
  <constraint name="c127" index="126" slack="0"/>
  <constraint name="c128" index="127" slack="-999"/>
  <constraint name="c129" index="128" slack="-999.67877300000009"/>
  <constraint name="c130" index="129" slack="-999"/>
  <constraint name="c131" index="130" slack="0"/>
  <constraint name="c132" index="131" slack="-2999.4788830000002"/>
  <constraint name="c133" index="132" slack="-999"/>
  <constraint name="c134" index="133" slack="0"/>
  <constraint name="c135" index="134" slack="-2900"/>
  <constraint name="c136" index="135" slack="-998"/>
  <constraint name="c137" index="136" slack="-1"/>
  <constraint name="c138" index="137" slack="-3999.5400340000006"/>
  <constraint name="c139" index="138" slack="0"/>
  <constraint name="c140" index="139" slack="-999"/>
  <constraint name="c141" index="140" slack="0"/>
  <constraint name="c142" index="141" slack="-998"/>
  <constraint name="c143" index="142" slack="-1"/>
  <constraint name="c144" index="143" slack="-2000.0066209999998"/>
  <constraint name="c145" index="144" slack="0"/>
  <constraint name="c146" index="145" slack="-999"/>
  <constraint name="c147" index="146" slack="-0.034241999999949257"/>
  <constraint name="c148" index="147" slack="-998"/>
  <constraint name="c149" index="148" slack="-1"/>
  <constraint name="c150" index="149" slack="-1000.3029049999999"/>
  <constraint name="c151" index="150" slack="0"/>
  <constraint name="c152" index="151" slack="-999"/>
  <constraint name="c153" index="152" slack="-0.30290499999996118"/>
  <constraint name="c154" index="153" slack="-998"/>
  <constraint name="c155" index="154" slack="-1"/>
  <constraint name="c156" index="155" slack="-2900.3750650000002"/>
  <constraint name="c157" index="156" slack="0"/>
  <constraint name="c158" index="157" slack="-999"/>
  <constraint name="c159" index="158" slack="-0.34631299999989551"/>
  <constraint name="c160" index="159" slack="-900.06080899999995"/>
  <constraint name="c161" index="160" slack="0"/>
  <constraint name="c162" index="161" slack="-900.06080899999995"/>
  <constraint name="c163" index="162" slack="0"/>
  <constraint name="c164" index="163" slack="-998"/>
  <constraint name="c165" index="164" slack="-1"/>
  <constraint name="c166" index="165" slack="-2900.4045689999998"/>
  <constraint name="c167" index="166" slack="0"/>
  <constraint name="c168" index="167" slack="-999"/>
  <constraint name="c169" index="168" slack="-0.37506499999994958"/>
  <constraint name="c170" index="169" slack="-998"/>
  <constraint name="c171" index="170" slack="-1"/>
  <constraint name="c172" index="171" slack="-1999.1146460000002"/>
  <constraint name="c173" index="172" slack="0"/>
  <constraint name="c174" index="173" slack="-999"/>
  <constraint name="c175" index="174" slack="-999.54630700000007"/>
  <constraint name="c176" index="175" slack="-998"/>
  <constraint name="c177" index="176" slack="-1"/>
  <constraint name="c178" index="177" slack="-1899.6249350000001"/>
  <constraint name="c179" index="178" slack="0"/>
  <constraint name="c180" index="179" slack="-999"/>
  <constraint name="c181" index="180" slack="-999.57976300000007"/>
  <constraint name="c182" index="181" slack="-998"/>
  <constraint name="c183" index="182" slack="-1"/>
  <constraint name="c184" index="183" slack="-2899.6857440000003"/>
  <constraint name="c185" index="184" slack="0"/>
  <constraint name="c186" index="185" slack="-999"/>
  <constraint name="c187" index="186" slack="-999.62493500000005"/>
  <constraint name="c188" index="187" slack="-900.02950399999997"/>
  <constraint name="c189" index="188" slack="0"/>
  <constraint name="c190" index="189" slack="-900.02950399999997"/>
  <constraint name="c191" index="190" slack="0"/>
  <constraint name="c192" index="191" slack="-999"/>
  <constraint name="c193" index="192" slack="0"/>
  <constraint name="c194" index="193" slack="-2999.6857439999999"/>
  <constraint name="c195" index="194" slack="-999"/>
  <constraint name="c196" index="195" slack="0"/>
  <constraint name="c197" index="196" slack="-2899.9461620000002"/>
  <constraint name="c198" index="197" slack="-998"/>
  <constraint name="c199" index="198" slack="-1"/>
  <constraint name="c200" index="199" slack="-2999.7468950000002"/>
  <constraint name="c201" index="200" slack="0"/>
  <constraint name="c202" index="201" slack="-999"/>
  <constraint name="c203" index="202" slack="-999.94616199999996"/>
  <constraint name="c204" index="203" slack="-998"/>
  <constraint name="c205" index="204" slack="-1"/>
  <constraint name="c206" index="205" slack="-1999.9458119999999"/>
  <constraint name="c207" index="206" slack="0"/>
  <constraint name="c208" index="207" slack="-999"/>
  <constraint name="c209" index="208" slack="0"/>
  <constraint name="c210" index="209" slack="-998"/>
  <constraint name="c211" index="210" slack="-1"/>
  <constraint name="c212" index="211" slack="-1000.2420959999999"/>
  <constraint name="c213" index="212" slack="0"/>
  <constraint name="c214" index="213" slack="-999"/>
  <constraint name="c215" index="214" slack="-0.26866300000001192"/>
  <constraint name="c216" index="215" slack="-998"/>
  <constraint name="c217" index="216" slack="-1"/>
  <constraint name="c218" index="217" slack="-1900.3142559999999"/>
  <constraint name="c219" index="218" slack="0"/>
  <constraint name="c220" index="219" slack="-999"/>
  <constraint name="c221" index="220" slack="-0.31207099999999943"/>
  <constraint name="c222" index="221" slack="-998"/>
  <constraint name="c223" index="222" slack="-1"/>
  <constraint name="c224" index="223" slack="-2900.3437599999997"/>
  <constraint name="c225" index="224" slack="0"/>
  <constraint name="c226" index="225" slack="-999"/>
  <constraint name="c227" index="226" slack="-0.34082300000000032"/>
  <constraint name="c228" index="227" slack="0"/>
  <constraint name="c229" index="228" slack="-900.26041799999996"/>
  <constraint name="c230" index="229" slack="-0.026567000000000007"/>
  <constraint name="c231" index="230" slack="-900.28698499999996"/>
  <constraint name="c232" index="231" slack="-998"/>
  <constraint name="c233" index="232" slack="-1"/>
  <constraint name="c234" index="233" slack="-1999.0851420000001"/>
  <constraint name="c235" index="234" slack="0"/>
  <constraint name="c236" index="235" slack="-999"/>
  <constraint name="c237" index="236" slack="-999.5168030000001"/>
  <constraint name="c238" index="237" slack="-998"/>
  <constraint name="c239" index="238" slack="-1"/>
  <constraint name="c240" index="239" slack="-1899.5954310000002"/>
  <constraint name="c241" index="240" slack="0"/>
  <constraint name="c242" index="241" slack="-999"/>
  <constraint name="c243" index="242" slack="-999.5502590000001"/>
  <constraint name="c244" index="243" slack="-998"/>
  <constraint name="c245" index="244" slack="-1"/>
  <constraint name="c246" index="245" slack="-1899.65624"/>
  <constraint name="c247" index="246" slack="0"/>
  <constraint name="c248" index="247" slack="-999"/>
  <constraint name="c249" index="248" slack="-999.59543100000008"/>
  <constraint name="c250" index="249" slack="-999"/>
  <constraint name="c251" index="250" slack="0"/>
  <constraint name="c252" index="251" slack="-2999.6562400000003"/>
  <constraint name="c253" index="252" slack="-999"/>
  <constraint name="c254" index="253" slack="0"/>
  <constraint name="c255" index="254" slack="-2899.9166580000001"/>
  <constraint name="c256" index="255" slack="-998"/>
  <constraint name="c257" index="256" slack="-1"/>
  <constraint name="c258" index="257" slack="-2999.7173910000001"/>
  <constraint name="c259" index="258" slack="0"/>
  <constraint name="c260" index="259" slack="-999"/>
  <constraint name="c261" index="260" slack="-999.91665799999998"/>
  <constraint name="c262" index="261" slack="-999"/>
  <constraint name="c263" index="262" slack="0"/>
  <constraint name="c264" index="263" slack="-2999.6853940000001"/>
  <constraint name="c265" index="264" slack="-999"/>
  <constraint name="c266" index="265" slack="0"/>
  <constraint name="c267" index="266" slack="-1999.713015"/>
  <constraint name="c268" index="267" slack="-999"/>
  <constraint name="c269" index="268" slack="0"/>
  <constraint name="c270" index="269" slack="-1999.9816779999999"/>
  <constraint name="c271" index="270" slack="-999"/>
  <constraint name="c272" index="271" slack="0"/>
  <constraint name="c273" index="272" slack="-1999.9816780000001"/>
  <constraint name="c274" index="273" slack="-999"/>
  <constraint name="c275" index="274" slack="0"/>
  <constraint name="c276" index="275" slack="-1900.053838"/>
  <constraint name="c277" index="276" slack="-999"/>
  <constraint name="c278" index="277" slack="0"/>
  <constraint name="c279" index="278" slack="-2000.0250860000001"/>
  <constraint name="c280" index="279" slack="-999"/>
  <constraint name="c281" index="280" slack="0"/>
  <constraint name="c282" index="281" slack="-1900.0833419999999"/>
  <constraint name="c283" index="282" slack="-999"/>
  <constraint name="c284" index="283" slack="0"/>
  <constraint name="c285" index="284" slack="-2000.0538379999998"/>
  <constraint name="c286" index="285" slack="-999.80073300000026"/>
  <constraint name="c287" index="286" slack="0"/>
  <constraint name="c288" index="287" slack="-999.80073300000026"/>
  <constraint name="c289" index="288" slack="0"/>
  <constraint name="c290" index="289" slack="-998"/>
  <constraint name="c291" index="290" slack="-1"/>
  <constraint name="c292" index="291" slack="-1999.6020519999997"/>
  <constraint name="c293" index="292" slack="0"/>
  <constraint name="c294" index="293" slack="-999"/>
  <constraint name="c295" index="294" slack="-999.68792900000005"/>
  <constraint name="c296" index="295" slack="-998"/>
  <constraint name="c297" index="296" slack="-1"/>
  <constraint name="c298" index="297" slack="-999.89833599999963"/>
  <constraint name="c299" index="298" slack="0"/>
  <constraint name="c300" index="299" slack="-999"/>
  <constraint name="c301" index="300" slack="-999.956592"/>
  <constraint name="c302" index="301" slack="-998"/>
  <constraint name="c303" index="302" slack="-1"/>
  <constraint name="c304" index="303" slack="-1899.9704959999997"/>
  <constraint name="c305" index="304" slack="0"/>
  <constraint name="c306" index="305" slack="-999"/>
  <constraint name="c307" index="306" slack="0"/>
  <constraint name="c308" index="307" slack="-998"/>
  <constraint name="c309" index="308" slack="-1"/>
  <constraint name="c310" index="309" slack="-1899.9999999999998"/>
  <constraint name="c311" index="310" slack="0"/>
  <constraint name="c312" index="311" slack="-999"/>
  <constraint name="c313" index="312" slack="-0.02875199999997444"/>
 </linearConstraints>
 <variables>
  <variable name="tt" index="0" value="0.48319699999990373"/>
  <variable name="s_1_1" index="1" value="0"/>
  <variable name="t_1_1" index="2" value="0.10166400000002795"/>
  <variable name="s_2_1" index="3" value="1"/>
  <variable name="t_2_1" index="4" value="0.10166399999997389"/>
  <variable name="s_1_2" index="5" value="0"/>
  <variable name="t_1_2" index="6" value="0.44974099999990269"/>
  <variable name="s_2_2" index="7" value="1"/>
  <variable name="t_2_2" index="8" value="0.44974099999990269"/>
  <variable name="s_1_3" index="9" value="0"/>
  <variable name="t_1_3" index="10" value="999.82264300000008"/>
  <variable name="s_2_3" index="11" value="1"/>
  <variable name="t_2_3" index="12" value="0.083341999999961947"/>
  <variable name="s_1_4" index="13" value="0"/>
  <variable name="t_1_4" index="14" value="0.40456899999992313"/>
  <variable name="s_2_4" index="15" value="1"/>
  <variable name="t_2_4" index="16" value="0.40456899999992313"/>
  <variable name="s_1_5" index="17" value="0"/>
  <variable name="t_1_5" index="18" value="0.02950399999997444"/>
  <variable name="s_2_5" index="19" value="1"/>
  <variable name="t_2_5" index="20" value="0.02950399999997444"/>
  <variable name="s_1_6" index="21" value="0"/>
  <variable name="t_1_6" index="22" value="0.34375999999992068"/>
  <variable name="s_2_6" index="23" value="1"/>
  <variable name="t_2_6" index="24" value="0.37032699999997387"/>
  <variable name="s_1_7" index="25" value="0"/>
  <variable name="t_1_7" index="26" value="0"/>
  <variable name="s_2_7" index="27" value="1"/>
  <variable name="t_2_7" index="28" value="0"/>
  <variable name="s_1_8" index="29" value="1"/>
  <variable name="t_1_8" index="30" value="0.083341999999961947"/>
  <variable name="s_2_8" index="31" value="0"/>
  <variable name="t_2_8" index="32" value="0.083341999999961947"/>
  <variable name="s_1_9" index="33" value="0"/>
  <variable name="t_1_9" index="34" value="-2.8438362775773385e-13"/>
  <variable name="s_2_9" index="35" value="1"/>
  <variable name="t_2_9" index="36" value="0.058255999999974439"/>
  <variable name="r_1_1_2" index="37" value="1"/>
  <variable name="u_1_1_2" index="38" value="-0"/>
  <variable name="r_2_1_2" index="39" value="0"/>
  <variable name="u_2_1_2" index="40" value="-0"/>
  <variable name="r_1_1_4" index="41" value="1"/>
  <variable name="u_1_1_4" index="42" value="-0"/>
  <variable name="r_2_1_4" index="43" value="0"/>
  <variable name="u_2_1_4" index="44" value="-0"/>
  <variable name="r_1_1_6" index="45" value="1"/>
  <variable name="u_1_1_6" index="46" value="-0"/>
  <variable name="r_2_1_6" index="47" value="0"/>
  <variable name="u_2_1_6" index="48" value="-0"/>
  <variable name="r_1_1_8" index="49" value="1"/>
  <variable name="u_1_1_8" index="50" value="1"/>
  <variable name="r_2_1_8" index="51" value="1"/>
  <variable name="u_2_1_8" index="52" value="-0"/>
  <variable name="r_1_1_9" index="53" value="1"/>
  <variable name="u_1_1_9" index="54" value="-0"/>
  <variable name="r_2_1_9" index="55" value="0"/>
  <variable name="u_2_1_9" index="56" value="1"/>
  <variable name="r_1_2_3" index="57" value="1"/>
  <variable name="u_1_2_3" index="58" value="-0"/>
  <variable name="r_2_2_3" index="59" value="0"/>
  <variable name="u_2_2_3" index="60" value="1"/>
  <variable name="r_1_2_5" index="61" value="1"/>
  <variable name="u_1_2_5" index="62" value="-0"/>
  <variable name="r_2_2_5" index="63" value="-0"/>
  <variable name="u_2_2_5" index="64" value="1"/>
  <variable name="r_1_2_7" index="65" value="1"/>
  <variable name="u_1_2_7" index="66" value="-0"/>
  <variable name="r_2_2_7" index="67" value="-0"/>
  <variable name="u_2_2_7" index="68" value="1"/>
  <variable name="r_1_3_4" index="69" value="1"/>
  <variable name="u_1_3_4" index="70" value="-0"/>
  <variable name="r_2_3_4" index="71" value="0"/>
  <variable name="u_2_3_4" index="72" value="-0"/>
  <variable name="r_1_3_6" index="73" value="1"/>
  <variable name="u_1_3_6" index="74" value="-0"/>
  <variable name="r_2_3_6" index="75" value="0"/>
  <variable name="u_2_3_6" index="76" value="-0"/>
  <variable name="r_1_3_8" index="77" value="1"/>
  <variable name="u_1_3_8" index="78" value="1"/>
  <variable name="r_2_3_8" index="79" value="1"/>
  <variable name="u_2_3_8" index="80" value="-0"/>
  <variable name="r_1_3_9" index="81" value="1"/>
  <variable name="u_1_3_9" index="82" value="-0"/>
  <variable name="r_2_3_9" index="83" value="0"/>
  <variable name="u_2_3_9" index="84" value="1"/>
  <variable name="r_1_4_5" index="85" value="1"/>
  <variable name="u_1_4_5" index="86" value="-0"/>
  <variable name="r_2_4_5" index="87" value="-0"/>
  <variable name="u_2_4_5" index="88" value="1"/>
  <variable name="r_1_4_7" index="89" value="1"/>
  <variable name="u_1_4_7" index="90" value="-0"/>
  <variable name="r_2_4_7" index="91" value="-0"/>
  <variable name="u_2_4_7" index="92" value="1"/>
  <variable name="r_1_5_6" index="93" value="1"/>
  <variable name="u_1_5_6" index="94" value="-0"/>
  <variable name="r_2_5_6" index="95" value="-0"/>
  <variable name="u_2_5_6" index="96" value="-0"/>
  <variable name="r_1_5_8" index="97" value="1"/>
  <variable name="u_1_5_8" index="98" value="-0"/>
  <variable name="r_2_5_8" index="99" value="1"/>
  <variable name="u_2_5_8" index="100" value="-0"/>
  <variable name="r_1_5_9" index="101" value="1"/>
  <variable name="u_1_5_9" index="102" value="-0"/>
  <variable name="r_2_5_9" index="103" value="-0"/>
  <variable name="u_2_5_9" index="104" value="-0"/>
  <variable name="r_1_6_7" index="105" value="1"/>
  <variable name="u_1_6_7" index="106" value="-0"/>
  <variable name="r_2_6_7" index="107" value="-0"/>
  <variable name="u_2_6_7" index="108" value="1"/>
  <variable name="r_1_7_8" index="109" value="1"/>
  <variable name="u_1_7_8" index="110" value="-0"/>
  <variable name="r_2_7_8" index="111" value="1"/>
  <variable name="u_2_7_8" index="112" value="-0"/>
  <variable name="r_1_7_9" index="113" value="1"/>
  <variable name="u_1_7_9" index="114" value="-0"/>
  <variable name="r_2_7_9" index="115" value="0"/>
  <variable name="u_2_7_9" index="116" value="-0"/>
 </variables>
</CPLEXSolution>
